{
  "id": "2.62",
  "name": "Output Ports and Port Output Trajectories",
  "description": "Definition of the set of output ports OPZ, the readout RjZ for each port, and the port output trajectories OTjZ generated by complete input trajectories.",
  "elements": [
    {
      "id": "2.62/definition/output_ports",
      "type": "component",
      "text": "The set of output ports of the system Z is denoted OPZ: {O1Z, ..., OnZ} if OZ is a product, or {OZ} otherwise."
    },
    {
      "id": "2.62/definition/port_readout",
      "type": "component",
      "text": "If #OPZ > 1 and j ∈ IJS[1, #OPZ], the readout to the jth output port is RjZ = PJN(OjZ) ∘ RZ."
    },
    {
      "id": "2.62/definition/port_output_trajectory",
      "type": "component",
      "text": "If #OPZ > 1, f ∈ ITZ, x ∈ SZ and j ∈ IJS[1, #OPZ], then the OjZ output port trajectory is OTjZ(f, x) = PJN(OjZ) ∘ OTZ(f, x)."
    }
  ]
}
